mahjong/__init__.py
mahjong/__main__.py
mahjong/game.py
mahjong/melds.py
mahjong/players.py
mahjong/tiles.py
python_mahjong-1.0.0.dist-info/LICENSE.txt
python_mahjong-1.0.0.dist-info/METADATA
python_mahjong-1.0.0.dist-info/WHEEL
python_mahjong-1.0.0.dist-info/top_level.txt
python_mahjong-1.0.0.dist-info/RECORD
