Metadata-Version: 2.1
Name: python-mahjong
Version: 1.0.0
Summary: Abstract away the logic of mahjong games.
Home-page: https://github.com/Kenny2github/mahjong
Author: Ken Hilton
License: LGPLv3+
Keywords: mahjong game engine
Platform: UNKNOWN
Classifier: Development Status :: 3 - Alpha
Classifier: Intended Audience :: Developers
Classifier: Topic :: Games/Entertainment :: Board Games
Classifier: Topic :: Games/Entertainment :: Turn Based Strategy
Classifier: License :: OSI Approved :: GNU General Public License v3 or later (GPLv3+)
Classifier: Programming Language :: Python :: 3.7
Requires-Python: >=3.7
